qface_store-1.1.dist-info/DESCRIPTION.rst
qface_store-1.1.dist-info/METADATA
qface_store-1.1.dist-info/RECORD
qface_store-1.1.dist-info/WHEEL
qface_store-1.1.dist-info/entry_points.txt
qface_store-1.1.dist-info/metadata.json
qface_store-1.1.dist-info/top_level.txt
store/__init__.py
store/store.py
store/templates/__init__.py
store/templates/libproject.pro
store/templates/project.pro
store/templates/qmake.conf
store/templates/shared/__init__.py
store/templates/shared/action.h
store/templates/shared/shared.pri
store/templates/stores/__init__.py
store/templates/stores/stores.pro
store/templates/stores/store/__init__.py
store/templates/stores/store/libstore.pro
store/templates/stores/store/plugin.cpp
store/templates/stores/store/plugin.h
store/templates/stores/store/state.cpp
store/templates/stores/store/state.h
store/templates/stores/store/state_p.h
store/templates/stores/store/store.cpp
store/templates/stores/store/store.h
store/templates/stores/store/store.pri
store/templates/stores/store/store.pro
store/templates/stores/store/storebase.cpp
store/templates/stores/store/storebase.h
