Metadata-Version: 2.0
Name: qface-store
Version: 1.1
Summary: Generator based on the QFace library for redux store concept
Home-page: https://github.com/Pelagicore/qface-store
Author: jryannel
Author-email: juergen@ryannel.org
License: MIT
Keywords: qt redux generator
Platform: UNKNOWN
Classifier: Development Status :: 3 - Alpha
Classifier: Intended Audience :: Developers
Classifier: Topic :: Software Development :: Code Generators
Classifier: License :: OSI Approved :: MIT License
Classifier: Programming Language :: Python :: 3
Requires-Dist: qface (>=1.3.1)
